{"content":[{"id":"events","heading":{"short":"Join Us","medium":"Explore Exciting Events in the IT Solutions Community","long":"Be Part of the Future of Technology - Attend Our Innovative Events"},"sentence":{"short":"Discover the latest in software engineering and web development.","medium":"Join Kev Kaariz and fellow tech enthusiasts to dive into cutting-edge solutions."},"overline":{"short":"Exclusive Event Access"},"button":{"short":"Join Now"},"secondary-button":{"short":"Learn More"}},{"id":"events-columns","columns":[{"title-medium":"Join Our Virtual Event: Building Scalable Websites with Custom WordPress Themes","sentence-medium":"Learn how to create efficient and fast websites using custom WordPress themes in this interactive online workshop."},{"title-medium":"Explore the Future of Web Development: User-Centric Solutions for Digital Platforms","sentence-medium":"Discover how to craft cutting-edge web solutions that enhance user experience and transform digital interactions."}]},{"id":"events-hero","heading":{"short":"Welcome","medium":"Join us for an unforgettable experience"},"sentence":{"short":"Explore innovation with us"},"overline":{"short":"Discover the future of technology"},"button":{"short":"Register now"},"secondary-button":{"short":"Learn more"},"cards":[{"title-short":"Innovative Solutions","sentence-short":"Join our community of tech enthusiasts","sentence-medium":"Be part of shaping the future of technology with us","button-short":"Join event"},{"title-short":"Cutting-edge Websites","sentence-short":"Experience the latest in web development","sentence-medium":"Discover the power of custom WordPress themes","button-short":"Explore now"},{"title-short":"User-centric Tools","sentence-short":"Transforming digital interactions","sentence-medium":"Crafting solutions that bridge creativity and technology","button-short":"Get involved"}]},{"id":"events-list","list":[{"list-item-short":"Join us for a coding workshop"},{"list-item-short":"Participate in a software engineering conference"},{"list-item-short":"Explore the world of custom WordPress themes"},{"list-item-short":"Learn about mobile-friendly website development"},{"list-item-short":"Discover the importance of SEO in IT solutions"},{"list-item-short":"Engage with experts in building vivid UI designs"}]},{"id":"events-videos","videos":[{"title-short":"Airbnb Clone Workshop"},{"title-short":"Simple WP Theme Tutorial"},{"title-short":"Mobile-friendly Design Tips"},{"title-short":"Exploring AMP and SEO Strategies"}]}]}